MANIFEST.in
README.md
setup.py
adyengo/__init__.py
adyengo/admin.py
adyengo/api.py
adyengo/constants.py
adyengo/managers.py
adyengo/models.py
adyengo/notification.py
adyengo/settings.py
adyengo/sites.py
adyengo/utils.py
adyengo/views.py
adyengo.egg-info/PKG-INFO
adyengo.egg-info/SOURCES.txt
adyengo.egg-info/dependency_links.txt
adyengo.egg-info/not-zip-safe
adyengo.egg-info/requires.txt
adyengo.egg-info/top_level.txt
adyengo/migrations/0001_initial.py
adyengo/migrations/0002_auto_20160428_1807.py
adyengo/migrations/0003_auto_20160519_1558.py
adyengo/migrations/0004_auto_20160526_0003.py
adyengo/migrations/0005_auto_20160527_2033.py
adyengo/migrations/0006_auto_20160527_2051.py
adyengo/migrations/0007_auto_20160527_2341.py
adyengo/migrations/0008_auto_20160527_2359.py
adyengo/migrations/0009_auto_20160528_0015.py
adyengo/migrations/0010_auto_20160528_0022.py
adyengo/migrations/0011_auto_20160608_1848.py
adyengo/migrations/0012_auto_20160610_1504.py
adyengo/migrations/0013_auto_20160707_1919.py
adyengo/migrations/0014_auto_20160707_2050.py
adyengo/migrations/0015_auto_20160707_2054.py
adyengo/migrations/0016_auto_20160707_2055.py
adyengo/migrations/0017_auto_20161013_1848.py
adyengo/migrations/0018_auto_20161013_1848.py
adyengo/migrations/0019_auto_20170303_1340.py
adyengo/migrations/0020_auto_20170616_1329.py
adyengo/migrations/0021_auto_20180912_1526.py
adyengo/migrations/0022_auto_20200519_0208.py
adyengo/migrations/__init__.py
adyengo/templates/adyengo/base.html
adyengo/templates/adyengo/api/execute_disable_recurring_contract.html
adyengo/templates/adyengo/api/execute_recurring_session.html
adyengo/templates/adyengo/api/execute_request_contracts.html
adyengo/templates/adyengo/api/setup_disable_recurring_contract.html
adyengo/templates/adyengo/api/setup_recurring_session.html
adyengo/templates/adyengo/api/setup_request_contracts.html
adyengo/templates/adyengo/hpp/dispatch_session.html
adyengo/templates/adyengo/hpp/result_page.html
adyengo/templates/adyengo/hpp/setup_session.html